ig_trading_historical_data/__init__.py
ig_trading_historical_data/ig_trading_historical_data.py
ig_trading_historical_data-1.0.0.dist-info/METADATA
ig_trading_historical_data-1.0.0.dist-info/WHEEL
ig_trading_historical_data-1.0.0.dist-info/licenses/LICENSE
ig_trading_historical_data-1.0.0.dist-info/RECORD
