Metadata-Version: 2.1
Name: ig_trading_historical_data
Version: 1.0.0
Summary: A Python wrapper for extracting historical data in a quota-efficient way from IG's Trading API (can specify a daily time range for data gathering).
Project-URL: Homepage, https://github.com/Shayan-H20/IG-Trading-Historical-Data
Project-URL: Issues, https://github.com/Shayan-H20/IG-Trading-Historical-Data/issues
Author-email: Shayan Mahinfar <shayanmahinfar@gmail.com>
License-File: LICENSE
Keywords: CFD,api,download market data,financial data,financial time series data,historical market data,ig,ig markets,ig trading,market data,spread betting,time series data,trading,trading api,trading data
Classifier: Intended Audience :: Financial and Insurance Industry
Classifier: Intended Audience :: Information Technology
Classifier: License :: OSI Approved :: BSD License
Classifier: Operating System :: OS Independent
Classifier: Programming Language :: Python :: 3
Classifier: Programming Language :: Python :: 3.9
Classifier: Programming Language :: Python :: 3.10
Classifier: Programming Language :: Python :: 3.11
Classifier: Programming Language :: Python :: 3.12
Classifier: Topic :: Internet :: WWW/HTTP
Classifier: Topic :: Internet :: WWW/HTTP :: HTTP Servers
Classifier: Topic :: Office/Business :: Financial
Classifier: Topic :: Office/Business :: Financial :: Investment
Requires-Python: >=3.9
Requires-Dist: numpy==1.26.3
Requires-Dist: pandas==2.1.4
Requires-Dist: requests-toolbelt==1.0.0
Requires-Dist: requests==2.31.0
